Workbook

Sheet Resumo
A1: Bot Interno Enleva — Estimativa de Custo de API
A2: Modelo editável para apresentação aos gestores. Ver aba 'Premissas' para ajustar os números.
A4: Apresentação: ver aba 'Intensidade 350' (faixa $2/$10 e $3/$15). Abaixo = Moderado clássico 600 colab. @ preço vigente $2/$10.
A5: Custo mensal estimado (USD) | B5: =Cenários!$E$6
A6: Custo mensal estimado (R$) | B6: =Cenários!$F$6
A7: Custo anual estimado (R$) | B7: =B6*12
A9: Pontos-chave para a apresentação:
A10: • O custo de API no cenário Moderado fica ~R$ 50/mês (Sonnet $2/$10). No Agressivo, Sonnet vs Gemini Flash-Lite fica ~R$ 115–120/mês de diferença — material na linha de API, ainda pequeno vs 1 FTE. Há tempo para bakeoff de qualidade antes de trocar provedor.
A11: • Preço Sonnet 5: vigente $2/$10 (Anthropic confirmou permanente em 10/08/2026; aumento a $3/$15 em 01/09 foi cancelado). A planilha ainda mostra $3/$15 como coluna de ESTRESSE na aba Intensidade 350 — para gestores verem a faixa, não porque o piloto 'vai pagar promo até 31/08'.
A12: • Este valor cobre só a API de IA — não inclui hospedagem/infraestrutura do servidor (item separado, normalmente já coberto pela infra existente da empresa).
A13: • O benefício principal NÃO é “economia em R$ por chamado evitado”. É otimização do trabalho de RH/TI (menos fila de FAQ repetitivo), redução de carga operacional e maior proximidade do colaborador com procedimentos oficiais dentro da plataforma da Rede Enleva. Ver aba "Benefício esperado".
A14: • Candidatas mais baratas (GPT-4o mini, Gemini Flash/Flash-Lite, ou Haiku como gerador) ficam na aba Comparativo Provedores — só entram em produção se empatar guardrails no bakeoff (ver docs/CUSTOS_LLM.md). Default do piloto permanece Anthropic Sonnet.
A15: • TCO (infra + API Sonnet vs Gemini): ver aba 'TCO Infra+API'. Ajuste os placeholders de host antes de apresentar.

Sheet Premissas
A1: Premissas — Bot Interno Enleva
A2: Células amarelas = editáveis. Ajuste conforme dados reais da empresa.
A4: Empresa
A5: Total de colaboradores | B5: 600
A6: Câmbio USD → BRL (R$) | B6: 5.3 | D6: Ajuste conforme cotação do dia da apresentação
A8: Preços da API Anthropic (USD por milhão de tokens) — FAIXA para gestores
A9: Modelo / cenário | B9: Entrada | C9: Saída | D9: Nota
A10: Sonnet 5 — vigente / permanente (usar como base) | B10: 2 | C10: 10 | D10: Preço oficial atual (consultado ago/2026). Em 10/08/2026 a Anthropic anunciou que $2/$10 deixou de ser só promocional até 31/08 e passou a ser o preço padrão; o aumento para $3/$15 em 01/09/2026 foi cancelado. Fonte: platform.claude.com/docs pricing.
A11: Sonnet 5 — cenário ESTRESSE $3/$15 (não é o list price vigente) | B11: 3 | C11: 15 | D11: Mantido na planilha só como sensibilidade conservadora (se o list price mudar no futuro ou para comparar com material antigo). NÃO apresentar como 'preço pós-31/08' — isso estava previsto e foi cancelado. Haiku permanece $1/$5 nas linhas abaixo.
A12: Claude Haiku 4.5 (classificador de escopo — stack atual) | B12: 1 | C12: 5 | D12: No stack atual Haiku só classifica escopo ambíguo. Fonte: platform.claude.com — pricing.
A13: Perfil de tokens por mensagem (Sonnet 5 — geração)
A14: System prompt (fixo) | B14: 400
A15: Contexto recuperado da base (RAG, média) | B15: 1200 | D15: Baseado em RETRIEVAL_TOP_K=4 chunks de ~500-800 tokens cada, nem sempre todos usados no máximo.
A16: Pergunta do colaborador (média) | B16: 30
A17: Histórico da conversa (média por mensagem) | B17: 300 | D17: Média ao longo da sessão (SESSION_MAX_TURNS=6); cresce nas mensagens seguintes de uma mesma conversa.
A19: Tom de resposta (tokens de saída médios)
A20: Direto / objetivo | B20: 90
A21: Amigável / acessível (recomendado) | B21: 220 | D21: Indicado para colaborador menos digital. Respostas mais explicativas e acolhedoras usam mais tokens de saída — impacto real no custo, mostrado lado a lado.
A23: Classificador de escopo (Haiku) — casos ambíguos
A24: % de mensagens que acionam o Haiku | B24: 0.2 | D24: A cascata de escopo (keywords → similaridade local) já filtra a maioria sem chamar API; só casos ambíguos chegam ao Haiku.
A25: Tokens de entrada do classificador | B25: 150
A26: Tokens de saída do classificador | B26: 10
A28: Cenários de adoção mensal
A29: Cenário | B29: % colaboradores ativos/mês | C29: Conversas/usuário/mês | D29: Mensagens/conversa
A30: Conservador | B30: 0.15 | C30: 2 | D30: 2.5
A31: Moderado | B31: 0.3 | C31: 3 | D31: 3
A32: Agressivo | B32: 0.5 | C32: 4 | D32: 3.5
A34: Benefício esperado (piloto) — indicadores operacionais, não ROI financeiro inventado
A35: Indicador a acompanhar no piloto | B35: Como medir / preencher | D35: PREENCHER com valor real de RH/TI, se disponível (custo de tempo do atendente). Valor de exemplo.
A36: % de conversas resolvidas sem abertura de chamado | B36: PREENCHER com dados do piloto (pesquisa rápida ou marcação no atendimento) | C36: Não usar preço fictício de chamado | D36: Estimativa conservadora — nem toda pergunta respondida pelo bot evitaria um chamado real.
A37: Tempo até resposta útil vs. fila RH/TI | B37: PREENCHER (ex.: minutos no bot vs. SLA médio de chamado)
A38: Uso dentro da intranet (sessões / colaboradores ativos) | B38: Já estimado nas abas de cenários; validar no piloto

Sheet Cálculo
A1: Cálculo — Custo por Mensagem
A2: Fórmulas ligadas à aba Premissas. Não edite esta aba diretamente.
A4: Custo por mensagem — Sonnet 5 (geração)
B5: Direto | C5: Amigável @ $2/$10 (vigente) | D5: Amigável @ $3/$15 (estresse)
A6: Tokens de entrada (system + RAG + pergunta + histórico) | B6: =Premissas!$B$14+Premissas!$B$15+Premissas!$B$16+Premissas!$B$17 | C6: =B6 | D6: =C6
A7: Tokens de saída | B7: =Premissas!$B$20 | C7: =Premissas!$B$21 | D7: =C7
A8: Custo de entrada (USD) | B8: =B6/1000000*Premissas!$B$10 | C8: =C6/1000000*Premissas!$B$10 | D8: =D6/1000000*Premissas!$B$11
A9: Custo de saída (USD) | B9: =B7/1000000*Premissas!$C$10 | C9: =C7/1000000*Premissas!$C$10 | D9: =D7/1000000*Premissas!$C$11
A10: Custo Sonnet por mensagem (USD) — geração | B10: =B8+B9 | C10: =C8+C9 | D10: =D8+D9
A12: Custo médio do classificador Haiku (ponderado pela % de casos ambíguos)
A13: Custo se acionado (USD) | B13: =(Premissas!$B$25/1000000*Premissas!$B$12)+(Premissas!$B$26/1000000*Premissas!$C$12)
A14: Custo médio ponderado por mensagem (USD) | B14: =B13*Premissas!$B$24
A16: Custo total por mensagem
B17: Direto | C17: Amigável | D17: Amigável @ $3/$15
A18: USD | B18: =B10+$B$14 | C18: =C10+$B$14 | D18: =D10+$B$14
A19: R$ | B19: =B18*Premissas!$B$6 | C19: =C18*Premissas!$B$6 | D19: =D18*Premissas!$B$6

Sheet Intensidade 350
A1: Cenários de intensidade — pico de usuários ativos no bot
A2: Origem do '350': estimativa informada pelo solicitante na discussão de custo (não veio de RH/TI formal nem inventada pelo modelo). Célula amarela = editável — confirmar com RH/TI antes de cravar na apresentação aos gestores.
A4: Usuários ativos no bot (pico / mês) | B4: 350 | D4: Empresa total (referência Premissas) | E4: =Premissas!B5
A5: Câmbio USD→BRL | B5: =Premissas!B6
A6: Dias úteis/mês (cenários intensos) | B6: 22
A8: Nível | B8: Como calcula msgs/mês | C8: Msgs/mês | D8: R$/mês @ $2/$10 | E8: R$/mês @ $3/$15 | F8: USD/mês @ $2/$10 | G8: USD/mês @ $3/$15
A9: Leve | B9: usuários × 2 conversas × 2,5 msgs | C9: =$B$4*2*2.5 | D9: =C9*Cálculo!$C$19 | E9: =C9*Cálculo!$D$19 | F9: =C9*Cálculo!$C$18 | G9: =C9*Cálculo!$D$18
A10: Moderada | B10: usuários × 3 conversas × 3 msgs | C10: =$B$4*3*3 | D10: =C10*Cálculo!$C$19 | E10: =C10*Cálculo!$D$19 | F10: =C10*Cálculo!$C$18 | G10: =C10*Cálculo!$D$18
A11: Forte | B11: usuários × 4 conversas × 3,5 msgs | C11: =$B$4*4*3.5 | D11: =C11*Cálculo!$C$19 | E11: =C11*Cálculo!$D$19 | F11: =C11*Cálculo!$C$18 | G11: =C11*Cálculo!$D$18
A12: Intensa | B12: 1 msg/usuário/dia útil | C12: =$B$4*$B$6*1 | D12: =C12*Cálculo!$C$19 | E12: =C12*Cálculo!$D$19 | F12: =C12*Cálculo!$C$18 | G12: =C12*Cálculo!$D$18
A13: Muito intensa | B13: 2 msgs/usuário/dia útil | C13: =$B$4*$B$6*2 | D13: =C13*Cálculo!$C$19 | E13: =C13*Cálculo!$D$19 | F13: =C13*Cálculo!$C$18 | G13: =C13*Cálculo!$D$18
A15: Leitura para gestores
A16: • Apresentar sempre FAIXA: coluna $2/$10 (preço vigente/permanente segundo Anthropic) e coluna $3/$15 (estresse). Não diga que em 01/09 o preço 'sobe' — o aumento previsto foi cancelado em 10/08/2026; a coluna estresse é só prudência orçamentária.
A17: • Piloto real (pós CG-SI) provavelmente roda sob o list price vigente na data do go-live. Revalidar platform.claude.com/docs pricing na semana do contrato.
A18: • Se o pico de 350 for confirmado por RH/TI, o nível Moderada/Forte é o mais útil para orçamento; Intensa/Muito intensa só se o bot virar hábito diário da maioria.
A19: • Recomendação de produto: piloto em Anthropic Sonnet; teto/alerta de gasto; se apertar, bakeoff Haiku-como-gerador (mesmo fornecedor) — não Gemini no caminho crítico do piloto.
A20: • Para infra + API na mesma página: aba 'TCO Infra+API' (economia Gemini não elimina o custo do servidor).

Sheet TCO Infra+API
A1: TCO mensal — Infraestrutura + API (Sonnet vs Gemini)
A2: Mesma infra para qualquer fornecedor de LLM. A economia do Gemini reduz só a parte variável (API) — não elimina o custo do host. Células amarelas = editáveis. Msgs/mês vêm da aba Intensidade 350 (usuários em B4 lá).
A4: Custo de infraestrutura (R$/mês) — PLACEHOLDERS
A5: Host dedicado bot (FastAPI + embeddings + Postgres + Django Admin) | B5: 450 | C5: Ajustar com cotação real de VPS/cloud Enleva
A6: Redis (quando entrar) — opcional / fase posterior | B6: 0 | C6: 0 se ainda não provisionado; ex. +30–80 se managed
A7: Observabilidade / backup / misc | B7: 50
A8: Total infra (R$/mês) | B8: =B5+B6+B7
A10: Câmbio | B10: =Premissas!B6
A11: Usuários (ref. Intensidade 350) | B11: ='Intensidade 350'!B4
A13: Nível | B13: Msgs/mês | C13: API Sonnet R$ ($2/$10) | D13: API Gemini Flash-Lite R$ | E13: API Gemini 3.6 Flash R$ | F13: Economia Lite vs Sonnet | G13: TCO Sonnet (infra+API) | H13: TCO Gemini Lite | I13: TCO Gemini Flash | J13: Lite economiza quanto do TCO Sonnet?
A14: ='Intensidade 350'!A9 | B14: ='Intensidade 350'!C9 | C14: ='Intensidade 350'!D9 | D14: =B14*'Comparativo Provedores'!$B$15*$B$10 | E14: =B14*'Comparativo Provedores'!$B$16*$B$10 | F14: =C14-D14 | G14: =$B$8+C14 | H14: =$B$8+D14 | I14: =$B$8+E14 | J14: =IF(G14=0,"-",F14/G14)
A15: ='Intensidade 350'!A10 | B15: ='Intensidade 350'!C10 | C15: ='Intensidade 350'!D10 | D15: =B15*'Comparativo Provedores'!$B$15*$B$10 | E15: =B15*'Comparativo Provedores'!$B$16*$B$10 | F15: =C15-D15 | G15: =$B$8+C15 | H15: =$B$8+D15 | I15: =$B$8+E15 | J15: =IF(G15=0,"-",F15/G15)
A16: ='Intensidade 350'!A11 | B16: ='Intensidade 350'!C11 | C16: ='Intensidade 350'!D11 | D16: =B16*'Comparativo Provedores'!$B$15*$B$10 | E16: =B16*'Comparativo Provedores'!$B$16*$B$10 | F16: =C16-D16 | G16: =$B$8+C16 | H16: =$B$8+D16 | I16: =$B$8+E16 | J16: =IF(G16=0,"-",F16/G16)
A17: ='Intensidade 350'!A12 | B17: ='Intensidade 350'!C12 | C17: ='Intensidade 350'!D12 | D17: =B17*'Comparativo Provedores'!$B$15*$B$10 | E17: =B17*'Comparativo Provedores'!$B$16*$B$10 | F17: =C17-D17 | G17: =$B$8+C17 | H17: =$B$8+D17 | I17: =$B$8+E17 | J17: =IF(G17=0,"-",F17/G17)
A18: ='Intensidade 350'!A13 | B18: ='Intensidade 350'!C13 | C18: ='Intensidade 350'!D13 | D18: =B18*'Comparativo Provedores'!$B$15*$B$10 | E18: =B18*'Comparativo Provedores'!$B$16*$B$10 | F18: =C18-D18 | G18: =$B$8+C18 | H18: =$B$8+D18 | I18: =$B$8+E18 | J18: =IF(G18=0,"-",F18/G18)
A20: Leitura para a conversa com gestão
A21: • Infra é custo FIXO do produto (host do bot + CMS + banco). Trocar Anthropic por Gemini não remove essa linha — só reduz a variável API.
A22: • No nível Moderada/Forte, a economia Lite vs Sonnet costuma ser dezenas a ~R$ 150/mês: relevante na fatura de API, pequena frente a um host de centenas de R$.
A23: • Narrativa recomendada: piloto em Sonnet (dossiê pronto); trilho Gemini em paralelo (lab + mini-dossiê SI) para quando o volume/teto apertar — sem atrasar o CG-SI atual.
A24: • Ajuste B5–B7 com a cotação real do provedor Enleva antes da apresentação. Defaults (450+50) são PLACEHOLDERS, não proposta comercial.
A25: • Gemini na tabela = preço Comparativo (Flash-Lite / 3.6 Flash), tom Amigável, API paga only — nunca free tier / AI Studio gratuito.
A27: Exemplo numérico (com placeholders atuais de infra)
A28: Se infra ≈ R$ 500 e Moderada (~3.150 msgs): TCO Sonnet ≈ 500+102 ≈ R$ 602; TCO Lite ≈ 500+~7 ≈ R$ 507 — economia ~R$ 95 (~16% do TCO), não 'metade da conta'.

Sheet Cenários
A1: Cenários — Custo Mensal Estimado
A2: Combina adoção (Premissas) com tom de resposta (Cálculo). Tudo aqui é fórmula.
A4: Cenário | B4: Mensagens/mês | C4: Custo mensal — Direto (USD) | D4: Custo mensal — Direto (R$) | E4: Custo mensal — Amigável (USD) | F4: Custo mensal — Amigável (R$)
A5: Conservador | B5: =Premissas!$B$30*Premissas!$B$5*Premissas!$C$30*Premissas!$D$30 | C5: =$B5*Cálculo!$B$18 | D5: =$B5*Cálculo!$B$19 | E5: =$B5*Cálculo!$C$18 | F5: =$B5*Cálculo!$C$19
A6: Moderado | B6: =Premissas!$B$31*Premissas!$B$5*Premissas!$C$31*Premissas!$D$31 | C6: =$B6*Cálculo!$B$18 | D6: =$B6*Cálculo!$B$19 | E6: =$B6*Cálculo!$C$18 | F6: =$B6*Cálculo!$C$19
A7: Agressivo | B7: =Premissas!$B$32*Premissas!$B$5*Premissas!$C$32*Premissas!$D$32 | C7: =$B7*Cálculo!$B$18 | D7: =$B7*Cálculo!$B$19 | E7: =$B7*Cálculo!$C$18 | F7: =$B7*Cálculo!$C$19

Sheet Benefício esperado
A1: Benefício esperado — Bot Interno Enleva
A2: Esta aba NÃO estima economia financeira por “preço de chamado”. O valor do bot é operacional e de experiência: otimizar o trabalho de RH/TI, reduzir carga de FAQ repetitivo e aproximar o colaborador dos procedimentos oficiais na plataforma da Rede Enleva.
A4: Cenário | B4: Mensagens/mês (ref. aba Cenários) | C4: Foco do benefício | D4: Indicador sugerido no piloto
A5: Conservador | B5: =Cenários!B5 | C5: Validar adoção inicial e qualidade das respostas sem sobrecarregar RH/TI com testes | D5: % dúvidas resolvidas no bot sem chamado + satisfação qualitativa
A6: Moderado (recomendado) | B6: =Cenários!B6 | C6: Redução perceptível de fila de FAQ repetitivo; self-service na intranet | D6: Volume de chamados FAQ (antes/depois) + uso mensal de colaboradores ativos
A7: Agressivo | B7: =Cenários!B7 | C7: Bot como canal habitual de primeira resposta para procedimentos internos | D7: Tempo médio até resposta útil vs. SLA de chamado + NPS interno do widget
A9: Nota para gestores
A10: Compare o custo de API (abas Resumo / Intensidade 350 — faixa $2/$10 e estresse $3/$15) com o custo de oportunidade de RH/TI. Não invente ROI por chamado. Confirmar o número de usuários ativos (célula B4 da Intensidade 350) com RH/TI.
A12: Custo de API (tom Amigável) — referência
A13: Cenário | B13: Custo API (R$/mês)
A14: Conservador | B14: =Cenários!F5
A15: Moderado | B15: =Cenários!F6
A16: Agressivo | B16: =Cenários!F7

Sheet Comparativo Provedores
A1: Comparativo — Anthropic vs OpenAI vs Gemini (tom Amigável)
A2: Mesmas premissas de tokens da aba Premissas. Só o preço por token muda. Haiku como gerador NÃO é o stack atual (hoje Haiku = escopo). OpenAI e Gemini são candidatas ao bakeoff.
A4: Preços — candidatas (USD por milhão de tokens)
A5: Modelo | B5: Entrada | C5: Saída | D5: Nota
A6: Gemini 3.1 Flash-Lite (mais barato) | B6: 0.25 | C6: 1.5 | D6: Gemini 2.5 Flash-Lite ($0,10/$0,40) mais barato, mas com aposentadoria anunciada — preferir 3.1 Flash-Lite como base barata Google.
A7: Gemini 3.6 Flash (faixa de qualidade) | B7: 1.5 | C7: 7.5 | D7: Fonte: ai.google.dev/gemini-api/docs/pricing (consultado 12/08/2026). Usar só API paga — nunca free tier.
A8: OpenAI GPT-4o mini | B8: 0.15 | C8: 0.6 | D8: Fonte: openai.com/api/pricing. Já suportado via LLM_PROVIDER=openai no projeto.
A10: Custo por mensagem — tom Amigável (USD) — só geração (sem ponderar Haiku de escopo do stack atual)
A11: Provedor / Modelo | B11: Custo por mensagem (USD)
A12: Claude Sonnet 5 (stack atual — geração) | B12: =(Premissas!$B$14+Premissas!$B$15+Premissas!$B$16+Premissas!$B$17)/1000000*Premissas!$B$10+Premissas!$B$21/1000000*Premissas!$C$10
A13: Claude Haiku 4.5 (HIPÓTESE: usado como gerador — NÃO é o stack atual) | B13: =(Premissas!$B$14+Premissas!$B$15+Premissas!$B$16+Premissas!$B$17)/1000000*Premissas!$B$12+Premissas!$B$21/1000000*Premissas!$C$12
A14: OpenAI GPT-4o mini (candidata bakeoff) | B14: =(Premissas!$B$14+Premissas!$B$15+Premissas!$B$16+Premissas!$B$17)/1000000*$B$8+Premissas!$B$21/1000000*$C$8
A15: Gemini 3.1 Flash-Lite (candidata bakeoff — barata) | B15: =(Premissas!$B$14+Premissas!$B$15+Premissas!$B$16+Premissas!$B$17)/1000000*$B$6+Premissas!$B$21/1000000*$C$6
A16: Gemini 3.6 Flash (candidata bakeoff — qualidade) | B16: =(Premissas!$B$14+Premissas!$B$15+Premissas!$B$16+Premissas!$B$17)/1000000*$B$7+Premissas!$B$21/1000000*$C$7
A18: Custo mensal por cenário (R$, tom Amigável)
A19: Cenário | B19: Mensagens/mês | C19: Sonnet 5 | D19: Haiku como gerador* | E19: GPT-4o mini | F19: Gemini Flash-Lite | G19: Gemini 3.6 Flash
A20: Conservador | B20: =Cenários!$B$5 | C20: =$B20*$B$12*Premissas!$B$6 | D20: =$B20*$B$13*Premissas!$B$6 | E20: =$B20*$B$14*Premissas!$B$6 | F20: =$B20*$B$15*Premissas!$B$6 | G20: =$B20*$B$16*Premissas!$B$6
A21: Moderado | B21: =Cenários!$B$6 | C21: =$B21*$B$12*Premissas!$B$6 | D21: =$B21*$B$13*Premissas!$B$6 | E21: =$B21*$B$14*Premissas!$B$6 | F21: =$B21*$B$15*Premissas!$B$6 | G21: =$B21*$B$16*Premissas!$B$6
A22: Agressivo | B22: =Cenários!$B$7 | C22: =$B22*$B$12*Premissas!$B$6 | D22: =$B22*$B$13*Premissas!$B$6 | E22: =$B22*$B$14*Premissas!$B$6 | F22: =$B22*$B$15*Premissas!$B$6 | G22: =$B22*$B$16*Premissas!$B$6
A23: * Haiku como gerador = hipótese de economia DENTRO da Anthropic; no código atual Haiku só classifica escopo.
A25: Leitura dos números
A26: • No cenário Agressivo (preço Sonnet vigente $2/$10), Sonnet vs Gemini Flash-Lite fica ~R$ 115–120/mês (não “poucas dezenas”). Dinheiro real na linha de API; ainda assim pequeno vs 1 FTE. Buscar a opção mais barata via bakeoff, sem pressa.
A27: • Modelos baratos (Flash-Lite, às vezes mini) podem falhar em seguir instruções/guardrails. Para este bot (recusa segura, fail-closed, tom consistente), qualidade manda: barato só ganha se empatar o Sonnet nos testes.
A28: • Trocar de fornecedor reabre governança (dossiê SI / DPA). Trocar só o modelo dentro da Anthropic (ex.: Haiku como gerador) é mais leve em SI, mas ainda exige bakeoff.
A29: • IMPORTANTE: a camada gratuita do Gemini (Google AI Studio) pode reutilizar conteúdo para melhorar produtos Google — incompatível com o dossiê. Qualquer teste Gemini = API paga com faturamento ativado, nunca free tier.
A30: • Recomendação agora: manter Sonnet em produção/piloto; usar esta aba + docs/CUSTOS_LLM.md para experimentar candidatas baratas com a mesma bateria de testes. Só trocar default se empatar guardrails.
